ToolXmind2Testcase/__init__.py
ToolXmind2Testcase/__main__.py
ToolXmind2Testcase/convert_xmind_to_excel.py
ToolXmind2Testcase_dev-0.0.8.dist-info/LICENSE
ToolXmind2Testcase_dev-0.0.8.dist-info/METADATA
ToolXmind2Testcase_dev-0.0.8.dist-info/WHEEL
ToolXmind2Testcase_dev-0.0.8.dist-info/entry_points.txt
ToolXmind2Testcase_dev-0.0.8.dist-info/top_level.txt
ToolXmind2Testcase_dev-0.0.8.dist-info/RECORD
