Metadata-Version: 2.1
Name: ToolXmind2Testcase-dev
Version: 0.0.8
Summary: 脑图转换为Excel
Home-page: UNKNOWN
Author: xu.nie
Author-email: xu.nie@shopee.com
License: UNKNOWN
Platform: UNKNOWN
Classifier: Programming Language :: Python :: 3
Classifier: License :: OSI Approved :: MIT License
Classifier: Operating System :: OS Independent
